langchain_trading_agents/__init__.py
langchain_trading_agents/contant.py
langchain_trading_agents/assistive_tools/assistive_tools_utils.py
langchain_trading_agents/assistive_tools/decision_maker_system_prompt_words/de.md
langchain_trading_agents/assistive_tools/decision_maker_system_prompt_words/en.md
langchain_trading_agents/assistive_tools/decision_maker_system_prompt_words/es.md
langchain_trading_agents/assistive_tools/decision_maker_system_prompt_words/fr.md
langchain_trading_agents/assistive_tools/decision_maker_system_prompt_words/ja.md
langchain_trading_agents/assistive_tools/decision_maker_system_prompt_words/kr.md
langchain_trading_agents/assistive_tools/decision_maker_system_prompt_words/profile_de.md
langchain_trading_agents/assistive_tools/decision_maker_system_prompt_words/profile_en.md
langchain_trading_agents/assistive_tools/decision_maker_system_prompt_words/profile_es.md
langchain_trading_agents/assistive_tools/decision_maker_system_prompt_words/profile_fr.md
langchain_trading_agents/assistive_tools/decision_maker_system_prompt_words/profile_ja.md
langchain_trading_agents/assistive_tools/decision_maker_system_prompt_words/profile_kr.md
langchain_trading_agents/assistive_tools/decision_maker_system_prompt_words/profile_ru.md
langchain_trading_agents/assistive_tools/decision_maker_system_prompt_words/profile_zh_cn.md
langchain_trading_agents/assistive_tools/decision_maker_system_prompt_words/profile_zh_tw.md
langchain_trading_agents/assistive_tools/decision_maker_system_prompt_words/ru.md
langchain_trading_agents/assistive_tools/decision_maker_system_prompt_words/zh_cn.md
langchain_trading_agents/assistive_tools/decision_maker_system_prompt_words/zh_tw.md
langchain_trading_agents/assistive_tools/economic_calendar_system_prompt_words/de.md
langchain_trading_agents/assistive_tools/economic_calendar_system_prompt_words/en.md
langchain_trading_agents/assistive_tools/economic_calendar_system_prompt_words/es.md
langchain_trading_agents-0.0.13.dist-info/METADATA
langchain_trading_agents-0.0.13.dist-info/WHEEL
langchain_trading_agents-0.0.13.dist-info/licenses/LICENSE
langchain_trading_agents-0.0.13.dist-info/RECORD
