Metadata-Version: 2.4
Name: langchain-trading-agents
Version: 0.0.13
Summary: AI trading agents driven by langchain,Simulates real-world financial company departments(manager,news,traditional indicator,price_action,economic_calendar,decision maker) free real-time and historical financial market data via HTTP and WebSocket APIs.specifically designed for AI quantitative trading/training.Multiple Timeframes,Multiple-Symbols-Multiple-Timeframes Alignment
Project-URL: Homepage, https://github.com/aitrados/langchain-trading-agents
Project-URL: Bug Tracker, https://github.com/aitrados/langchain-trading-agents/issues
Project-URL: Repository, https://github.com/aitrados/langchain-trading-agents
Project-URL: Documentation, https://github.com/aitrados/langchain-trading-agents
Author-email: Alexander <support@aitrados.com>
License: MIT License
License-File: LICENSE
Keywords: AI,ai trade,ai trading,aitrados,api,financial,langchain,market-data,ohlc,ohlcv,quantitative,real-time,streaming ohlc,trade agents,trading agents,websockes ohlc,ws ohlc
Classifier: Environment :: Console
Classifier: Environment :: Web Environment
Classifier: Intended Audience :: Developers
Classifier: Intended Audience :: Financial and Insurance Industry
Classifier: License :: OSI Approved :: MIT License
Classifier: Operating System :: OS Independent
Classifier: Programming Language :: Python :: 3
Classifier: Programming Language :: Python :: 3.10
Classifier: Programming Language :: Python :: 3.11
Classifier: Programming Language :: Python :: 3.12
Classifier: Programming Language :: Python :: 3.13
Classifier: Programming Language :: Python :: 3.14
Classifier: Topic :: Office/Business :: Financial
Classifier: Topic :: Office/Business :: Financial :: Investment
Classifier: Topic :: Scientific/Engineering :: Information Analysis
Classifier: Topic :: Software Development :: Libraries :: Python Modules
Requires-Python: >=3.10
Requires-Dist: dashscope>=1.24.9
Requires-Dist: finance-trading-ai-agents-mcp>=0.0.9
Requires-Dist: langchain-anthropic>=1.0.1
Requires-Dist: langchain-community>=0.4.1
Requires-Dist: langchain-deepseek>=1.0.0
Requires-Dist: langchain-google-genai>=3.0.0
Requires-Dist: langchain-huggingface>=1.0.0
Requires-Dist: langchain-ollama>=1.0.0
Requires-Dist: langchain-openai>=1.0.1
Requires-Dist: langchain-xai>=1.0.0
Requires-Dist: langchain>=1.0.3
Requires-Dist: langgraph>=1.0.2
